fasttextlt/__init__.py
fasttextlt/fasttext.py
fasttextlt/format.py
fasttextlt-0.2.0.dist-info/licenses/LICENCE.md
fasttextlt-0.2.0.dist-info/METADATA
fasttextlt-0.2.0.dist-info/WHEEL
fasttextlt-0.2.0.dist-info/top_level.txt
fasttextlt-0.2.0.dist-info/RECORD
