Metadata-Version: 2.4
Name: fasttextlt
Version: 0.2.0
Summary: A pure Python FastText model reader
Author-email: Morgan Grobol <morgan.grobol@tuta.com>
License-Expression: LGPL-2.1-only
Project-URL: Bug Tracker, https://github.com/LoicGrobol/fasttextlt/issues
Project-URL: Changes, https://github.com/LoicGrobol/fasttextlt/blob/main/CHANGELOG.md
Project-URL: Source Code, https://github.com/LoicGrobol/fasttextlt
Keywords: nlp,embeddings,fasttext
Requires-Python: >=3.11
License-File: LICENCE.md
Requires-Dist: numpy<3,>=2
Dynamic: license-file
